sphinx_ansible_theme/__init__.py
sphinx_ansible_theme/built_with.html
sphinx_ansible_theme/extrabody.html
sphinx_ansible_theme/extrafooter.html
sphinx_ansible_theme/extrahead.html
sphinx_ansible_theme/extranav.html
sphinx_ansible_theme/footer.html
sphinx_ansible_theme/layout.html
sphinx_ansible_theme/py.typed
sphinx_ansible_theme/rtd-ethical-ads.html
sphinx_ansible_theme/searchbox.html
sphinx_ansible_theme/theme.conf
sphinx_ansible_theme/version_chooser.html
sphinx_ansible_theme/versions.html
sphinx_ansible_theme/static/css/ansible.css
sphinx_ansible_theme/static/css/rtd-ethical-ads.css
sphinx_ansible_theme/static/images/Ansible-Mark-RGB_Black.png
sphinx_ansible_theme/static/images/Ansible-Mark-RGB_Black.svg
sphinx_ansible_theme/static/images/Ansible-Mark-RGB_White.png
sphinx_ansible_theme/static/images/Ansible-Mark-RGB_White.svg
sphinx_ansible_theme-0.10.3.dist-info/LICENSE
sphinx_ansible_theme-0.10.3.dist-info/METADATA
sphinx_ansible_theme-0.10.3.dist-info/WHEEL
sphinx_ansible_theme-0.10.3.dist-info/entry_points.txt
sphinx_ansible_theme-0.10.3.dist-info/top_level.txt
sphinx_ansible_theme-0.10.3.dist-info/RECORD
